{
    "title": "Warm Gun will be live streamed - tune in this Friday",
    "slug": "warm-gun-will-be-live-streamed-tune-in-this-friday",
    "date": "2010-10-06T17:54:57.000Z",
    "url": "http://blog.500startups.com/?p=1116714274",
    "uri": "http://500.co/2010/10/06/warm-gun-will-be-live-streamed-tune-in-this-friday/",
    "postId": "1116714274",
    "description": "",
    "images": [
        "http://500.co/wp-content/uploads/2010/10/warmgun.jpg?w=300"
    ],
    "creator": "",
    "categories": [
        "design",
        "events",
        "events",
        "live-stream",
        "livestream",
        "warm-gun"
    ],
    "content": "<a href=\"http://500.co/wp-content/uploads/2010/10/warmgun.jpg\"><img class=\"alignnone size-medium wp-image-1116714275\" title=\"warmgun\" src=\"http://500.co/wp-content/uploads/2010/10/warmgun.jpg?w=300\" alt=\"\" width=\"300\" height=\"200\" /></a>\n\nOur first 500 Startups event, <a href=\"http://warmgun.com\">Warm Gun</a>, is only a couple days away!\n\nFor folks who can't make it in person, we'll be live streaming the event. So you can check out all the great sessions from wherever you are. The URL to bookmark: <a href=\"http://bit.ly/warmgunlivestream\"><strong>http://bit.ly/warmgunlivestream</strong></a>\n\nBe sure to follow <a href=\"http://twitter.com/warmgundesign\">@warmgundesign</a> for all the latest Warm Gun info, including day-of live tweeting and presenters' SlideShare presentations! And our event hash tags will be #warmgun and #warmgundesign.",
    "type": "post",
    "path": "/2010/10/06/warm-gun-will-be-live-streamed-tune-in-this-friday/"
}